{"config":{"output_file":null,"full_docs":false,"pub_only":true,"reachable_only":true,"distro_crate":false,"signatures":false,"borrow_data":false},"version":"0.19.0","compilation":{"directory":"/home/titus/.cargo/registry/src/github.com-1ecc6299db9ec823/scoped_threadpool-0.1.9","program":"/home/titus/.rustup/toolchains/stable-x86_64-unknown-linux-gnu/bin/rls","arguments":["--crate-name","scoped_threadpool","/home/titus/.cargo/registry/src/github.com-1ecc6299db9ec823/scoped_threadpool-0.1.9/src/lib.rs","--json=diagnostic-rendered-ansi","--crate-type","lib","--emit=dep-info,metadata","-C","debuginfo=2","-C","metadata=1a6172e014d5cdf4","-C","extra-filename=-1a6172e014d5cdf4","--out-dir","/home/titus/writing/school-related/gymnasie-arbete/program/target/rls/debug/deps","-L","dependency=/home/titus/writing/school-related/gymnasie-arbete/program/target/rls/debug/deps","--cap-lints","allow","--error-format=json","--sysroot","/home/titus/.rustup/toolchains/stable-x86_64-unknown-linux-gnu"],"output":"/home/titus/writing/school-related/gymnasie-arbete/program/target/rls/debug/deps/libscoped_threadpool-1a6172e014d5cdf4.rmeta"},"prelude":{"crate_id":{"name":"scoped_threadpool","disambiguator":[14611099944053313802,6276053386434190159]},"crate_root":"/home/titus/.cargo/registry/src/github.com-1ecc6299db9ec823/scoped_threadpool-0.1.9/src","external_crates":[{"file_name":"/home/titus/.cargo/registry/src/github.com-1ecc6299db9ec823/scoped_threadpool-0.1.9/src/lib.rs","num":1,"id":{"name":"std","disambiguator":[14071373652398347879,7103549041170480253]}},{"file_name":"/home/titus/.cargo/registry/src/github.com-1ecc6299db9ec823/scoped_threadpool-0.1.9/src/lib.rs","num":2,"id":{"name":"core","disambiguator":[5273437404553270099,5411348343046199890]}},{"file_name":"/home/titus/.cargo/registry/src/github.com-1ecc6299db9ec823/scoped_threadpool-0.1.9/src/lib.rs","num":3,"id":{"name":"compiler_builtins","disambiguator":[976218546544352998,2134245565175613459]}},{"file_name":"/home/titus/.cargo/registry/src/github.com-1ecc6299db9ec823/scoped_threadpool-0.1.9/src/lib.rs","num":4,"id":{"name":"rustc_std_workspace_core","disambiguator":[13100362557277821204,18082047403827332368]}},{"file_name":"/home/titus/.cargo/registry/src/github.com-1ecc6299db9ec823/scoped_threadpool-0.1.9/src/lib.rs","num":5,"id":{"name":"alloc","disambiguator":[3605767859335716447,18368004652892255649]}},{"file_name":"/home/titus/.cargo/registry/src/github.com-1ecc6299db9ec823/scoped_threadpool-0.1.9/src/lib.rs","num":6,"id":{"name":"libc","disambiguator":[7644919710974821109,7113146966867899407]}},{"file_name":"/home/titus/.cargo/registry/src/github.com-1ecc6299db9ec823/scoped_threadpool-0.1.9/src/lib.rs","num":7,"id":{"name":"unwind","disambiguator":[16182386318199163571,1953714320961812]}},{"file_name":"/home/titus/.cargo/registry/src/github.com-1ecc6299db9ec823/scoped_threadpool-0.1.9/src/lib.rs","num":8,"id":{"name":"cfg_if","disambiguator":[12664401352052491985,6928826529401171483]}},{"file_name":"/home/titus/.cargo/registry/src/github.com-1ecc6299db9ec823/scoped_threadpool-0.1.9/src/lib.rs","num":9,"id":{"name":"backtrace","disambiguator":[17274879524252775070,15165904048009513825]}},{"file_name":"/home/titus/.cargo/registry/src/github.com-1ecc6299db9ec823/scoped_threadpool-0.1.9/src/lib.rs","num":10,"id":{"name":"rustc_demangle","disambiguator":[3349673540409454496,14630436784565510244]}},{"file_name":"/home/titus/.cargo/registry/src/github.com-1ecc6299db9ec823/scoped_threadpool-0.1.9/src/lib.rs","num":11,"id":{"name":"backtrace_sys","disambiguator":[14546748579478228105,1074460191194833292]}},{"file_name":"/home/titus/.cargo/registry/src/github.com-1ecc6299db9ec823/scoped_threadpool-0.1.9/src/lib.rs","num":12,"id":{"name":"hashbrown","disambiguator":[5671097699487010686,7534711367382902334]}},{"file_name":"/home/titus/.cargo/registry/src/github.com-1ecc6299db9ec823/scoped_threadpool-0.1.9/src/lib.rs","num":13,"id":{"name":"rustc_std_workspace_alloc","disambiguator":[7229860330014108182,6606161976056509340]}},{"file_name":"/home/titus/.cargo/registry/src/github.com-1ecc6299db9ec823/scoped_threadpool-0.1.9/src/lib.rs","num":14,"id":{"name":"panic_unwind","disambiguator":[7609715969379266585,5596137465280250730]}}],"span":{"file_name":"/home/titus/.cargo/registry/src/github.com-1ecc6299db9ec823/scoped_threadpool-0.1.9/src/lib.rs","byte_start":0,"byte_end":15322,"line_start":1,"line_end":518,"column_start":1,"column_end":2}},"imports":[],"defs":[{"kind":"Mod","id":{"krate":0,"index":0},"span":{"file_name":"/home/titus/.cargo/registry/src/github.com-1ecc6299db9ec823/scoped_threadpool-0.1.9/src/lib.rs","byte_start":0,"byte_end":15322,"line_start":1,"line_end":518,"column_start":1,"column_end":2},"name":"","qualname":"::","value":"/home/titus/.cargo/registry/src/github.com-1ecc6299db9ec823/scoped_threadpool-0.1.9/src/lib.rs","parent":null,"children":[{"krate":0,"index":1},{"krate":0,"index":2},{"krate":0,"index":3},{"krate":0,"index":6},{"krate":0,"index":13},{"krate":0,"index":16},{"krate":0,"index":17},{"krate":0,"index":18},{"krate":0,"index":24},{"krate":0,"index":26},{"krate":0,"index":29},{"krate":0,"index":31},{"krate":0,"index":33},{"krate":0,"index":36},{"krate":0,"index":40},{"krate":0,"index":49},{"krate":0,"index":54},{"krate":0,"index":62}],"decl_id":null,"docs":" This crate provides a stable, safe and scoped threadpool.","sig":null,"attributes":[{"value":"warn(missing_docs)","span":{"file_name":"/home/titus/.cargo/registry/src/github.com-1ecc6299db9ec823/scoped_threadpool-0.1.9/src/lib.rs","byte_start":1656,"byte_end":1678,"line_start":48,"line_end":48,"column_start":1,"column_end":23}}]},{"kind":"Struct","id":{"krate":0,"index":33},"span":{"file_name":"/home/titus/.cargo/registry/src/github.com-1ecc6299db9ec823/scoped_threadpool-0.1.9/src/lib.rs","byte_start":2360,"byte_end":2364,"line_start":85,"line_end":85,"column_start":12,"column_end":16},"name":"Pool","qualname":"::Pool","value":"Pool {  }","parent":null,"children":[{"krate":0,"index":34},{"krate":0,"index":35}],"decl_id":null,"docs":" A threadpool that acts as a handle to a number\n of threads spawned at construction.\n","sig":null,"attributes":[]},{"kind":"Method","id":{"krate":0,"index":41},"span":{"file_name":"/home/titus/.cargo/registry/src/github.com-1ecc6299db9ec823/scoped_threadpool-0.1.9/src/lib.rs","byte_start":2690,"byte_end":2693,"line_start":99,"line_end":99,"column_start":12,"column_end":15},"name":"new","qualname":"<Pool>::new","value":"fn (n: u32) -> Pool","parent":null,"children":[],"decl_id":null,"docs":" Construct a threadpool with the given number of threads.\n Minimum value is `1`.\n","sig":null,"attributes":[]},{"kind":"Method","id":{"krate":0,"index":43},"span":{"file_name":"/home/titus/.cargo/registry/src/github.com-1ecc6299db9ec823/scoped_threadpool-0.1.9/src/lib.rs","byte_start":5396,"byte_end":5402,"line_start":174,"line_end":174,"column_start":12,"column_end":18},"name":"scoped","qualname":"<Pool>::scoped","value":"fn <'pool, 'scope, F, R> (&'pool mut self, f: F) -> R","parent":null,"children":[],"decl_id":null,"docs":" Borrows the pool and allows executing jobs on other\n threads during that scope via the argument of the closure.","sig":null,"attributes":[]},{"kind":"Method","id":{"krate":0,"index":48},"span":{"file_name":"/home/titus/.cargo/registry/src/github.com-1ecc6299db9ec823/scoped_threadpool-0.1.9/src/lib.rs","byte_start":5699,"byte_end":5711,"line_start":185,"line_end":185,"column_start":12,"column_end":24},"name":"thread_count","qualname":"<Pool>::thread_count","value":"fn (&self) -> u32","parent":null,"children":[],"decl_id":null,"docs":" Returns the number of threads inside this pool.\n","sig":null,"attributes":[]},{"kind":"Struct","id":{"krate":0,"index":49},"span":{"file_name":"/home/titus/.cargo/registry/src/github.com-1ecc6299db9ec823/scoped_threadpool-0.1.9/src/lib.rs","byte_start":5926,"byte_end":5931,"line_start":193,"line_end":193,"column_start":12,"column_end":17},"name":"Scope","qualname":"::Scope","value":"Scope {  }","parent":null,"children":[{"krate":0,"index":52},{"krate":0,"index":53}],"decl_id":null,"docs":" Handle to the scope during which the threadpool is borrowed.\n","sig":null,"attributes":[]},{"kind":"Method","id":{"krate":0,"index":57},"span":{"file_name":"/home/titus/.cargo/registry/src/github.com-1ecc6299db9ec823/scoped_threadpool-0.1.9/src/lib.rs","byte_start":6346,"byte_end":6353,"line_start":205,"line_end":205,"column_start":12,"column_end":19},"name":"execute","qualname":"<Scope>::execute","value":"fn <F> (&self, f: F) -> ()","parent":null,"children":[],"decl_id":null,"docs":" Execute a job on the threadpool.","sig":null,"attributes":[]},{"kind":"Method","id":{"krate":0,"index":61},"span":{"file_name":"/home/titus/.cargo/registry/src/github.com-1ecc6299db9ec823/scoped_threadpool-0.1.9/src/lib.rs","byte_start":6786,"byte_end":6794,"line_start":217,"line_end":217,"column_start":12,"column_end":20},"name":"join_all","qualname":"<Scope>::join_all","value":"fn (&self) -> ()","parent":null,"children":[],"decl_id":null,"docs":" Blocks until all currently queued jobs have run to completion.\n","sig":null,"attributes":[]}],"impls":[{"id":0,"kind":"Direct","span":{"file_name":"/home/titus/.cargo/registry/src/github.com-1ecc6299db9ec823/scoped_threadpool-0.1.9/src/lib.rs","byte_start":2066,"byte_end":2067,"line_start":69,"line_end":69,"column_start":29,"column_end":30},"value":"","parent":null,"children":[{"krate":0,"index":28}],"docs":"","sig":null,"attributes":[]},{"id":1,"kind":"Direct","span":{"file_name":"/home/titus/.cargo/registry/src/github.com-1ecc6299db9ec823/scoped_threadpool-0.1.9/src/lib.rs","byte_start":2185,"byte_end":2189,"line_start":77,"line_end":77,"column_start":15,"column_end":19},"value":"","parent":null,"children":[{"krate":0,"index":32}],"docs":"","sig":null,"attributes":[]},{"id":2,"kind":"Inherent","span":{"file_name":"/home/titus/.cargo/registry/src/github.com-1ecc6299db9ec823/scoped_threadpool-0.1.9/src/lib.rs","byte_start":2577,"byte_end":2581,"line_start":96,"line_end":96,"column_start":6,"column_end":10},"value":"","parent":null,"children":[{"krate":0,"index":41},{"krate":0,"index":43},{"krate":0,"index":48}],"docs":"","sig":null,"attributes":[]},{"id":3,"kind":"Inherent","span":{"file_name":"/home/titus/.cargo/registry/src/github.com-1ecc6299db9ec823/scoped_threadpool-0.1.9/src/lib.rs","byte_start":6113,"byte_end":6118,"line_start":199,"line_end":199,"column_start":21,"column_end":26},"value":"","parent":null,"children":[{"krate":0,"index":57},{"krate":0,"index":59},{"krate":0,"index":61}],"docs":"","sig":null,"attributes":[]},{"id":4,"kind":"Direct","span":{"file_name":"/home/titus/.cargo/registry/src/github.com-1ecc6299db9ec823/scoped_threadpool-0.1.9/src/lib.rs","byte_start":7816,"byte_end":7821,"line_start":246,"line_end":246,"column_start":30,"column_end":35},"value":"","parent":null,"children":[{"krate":0,"index":65}],"docs":"","sig":null,"attributes":[]}],"refs":[],"macro_refs":[],"relations":[{"span":{"file_name":"/home/titus/.cargo/registry/src/github.com-1ecc6299db9ec823/scoped_threadpool-0.1.9/src/lib.rs","byte_start":2066,"byte_end":2067,"line_start":69,"line_end":69,"column_start":29,"column_end":30},"kind":{"Impl":{"id":0}},"from":{"krate":0,"index":27},"to":{"krate":0,"index":24}},{"span":{"file_name":"/home/titus/.cargo/registry/src/github.com-1ecc6299db9ec823/scoped_threadpool-0.1.9/src/lib.rs","byte_start":2185,"byte_end":2189,"line_start":77,"line_end":77,"column_start":15,"column_end":19},"kind":{"Impl":{"id":1}},"from":{"krate":0,"index":33},"to":{"krate":2,"index":1726}},{"span":{"file_name":"/home/titus/.cargo/registry/src/github.com-1ecc6299db9ec823/scoped_threadpool-0.1.9/src/lib.rs","byte_start":2577,"byte_end":2581,"line_start":96,"line_end":96,"column_start":6,"column_end":10},"kind":{"Impl":{"id":2}},"from":{"krate":0,"index":33},"to":{"krate":4294967295,"index":4294967295}},{"span":{"file_name":"/home/titus/.cargo/registry/src/github.com-1ecc6299db9ec823/scoped_threadpool-0.1.9/src/lib.rs","byte_start":6113,"byte_end":6118,"line_start":199,"line_end":199,"column_start":21,"column_end":26},"kind":{"Impl":{"id":3}},"from":{"krate":0,"index":49},"to":{"krate":4294967295,"index":4294967295}},{"span":{"file_name":"/home/titus/.cargo/registry/src/github.com-1ecc6299db9ec823/scoped_threadpool-0.1.9/src/lib.rs","byte_start":7816,"byte_end":7821,"line_start":246,"line_end":246,"column_start":30,"column_end":35},"kind":{"Impl":{"id":4}},"from":{"krate":0,"index":49},"to":{"krate":2,"index":1726}}]}